bitstamp/__init__.py
bitstamp/client.py
BitstampClient-2.2.8.dist-info/LICENSE.txt
BitstampClient-2.2.8.dist-info/METADATA
BitstampClient-2.2.8.dist-info/WHEEL
BitstampClient-2.2.8.dist-info/top_level.txt
BitstampClient-2.2.8.dist-info/RECORD
