Metadata-Version: 2.1
Name: BitstampClient
Version: 2.2.8
Summary: Bitstamp API python implementation
Home-page: https://github.com/kmadac/bitstamp-python-client
Author: Kamil Madac
Author-email: kamil.madac@gmail.com
License: MIT
Platform: UNKNOWN
Requires-Dist: requests
